ambra/__init__.py
ambra/camera.py
ambra/config.py
ambra/ffx.py
ambra/geometry.py
ambra/gpu_property.py
ambra/gpu_sorting.py
ambra/headless.py
ambra/keybindings.py
ambra/lights.py
ambra/marching_cubes.py
ambra/materials.py
ambra/primitives2d.py
ambra/primitives3d.py
ambra/property.py
ambra/reflection.py
ambra/renderer.py
ambra/renderer_frame.py
ambra/scene.py
ambra/server.py
ambra/shaders.py
ambra/transform2d.py
ambra/transform3d.py
ambra/viewer.py
ambra/viewport.py
ambra/shaders/2d/basic.slang
ambra/shaders/2d/basic_texture.slang
ambra/shaders/2d/scene.slang
ambra/shaders/3d/basic.slang
ambra/shaders/3d/colormap.slang
ambra/shaders/3d/cube.slang
ambra/shaders/3d/grid.slang
ambra/shaders/3d/ibl.slang
ambra/shaders/3d/mesh.slang
ambra/shaders/3d/mesh_depth.slang
ambra/shaders/3d/points.slang
ambra/shaders/3d/scene.slang
ambra/shaders/3d/scene_depth.slang
ambra/shaders/3d/utils.slang
ambra/shaders/3d/voxels.slang
ambra/shaders/3d/gaussian_splatting/dist.comp.slang
ambra/shaders/3d/gaussian_splatting/shaderio.h.slang
ambra/shaders/3d/gaussian_splatting/threedgs.h.slang
ambra/shaders/3d/gaussian_splatting/threedgs_particles_storage.h.slang
ambra/shaders/3d/gaussian_splatting/threedgs_raster.frag.slang
ambra/shaders/3d/gaussian_splatting/threedgs_raster.mesh.slang
ambra/shaders/3d/gaussian_splatting/threedgs_raster.vert.slang
ambra/shaders/3d/gaussian_splatting/wireframe.h.slang
ambra/shaders/3d/marching_cubes/check_surface.slang
ambra/shaders/3d/marching_cubes/common.slang
ambra/shaders/3d/marching_cubes/compact.slang
ambra/shaders/3d/marching_cubes/marching_cubes.slang
ambra/shaders/3d/marching_cubes/tables.slang
ambra/shaders/3d/path_tracer/brdf.slang
ambra/shaders/3d/path_tracer/path_tracer.slang
ambra/shaders/GPUSorting/DeviceRadixSort.slang
ambra/shaders/GPUSorting/OneSweep.slang
ambra/shaders/GPUSorting/SortCommon.slang
ambra/shaders/GPUSorting/SweepCommon.slang
ambra/shaders/ffx/ffx_common_types.h
ambra/shaders/ffx/ffx_core.h
ambra-0.0.2.dist-info/METADATA
ambra-0.0.2.dist-info/WHEEL
ambra-0.0.2.dist-info/licenses/LICENSE
ambra-0.0.2.dist-info/RECORD
