Metadata-Version: 2.4
Name: ambra
Version: 0.0.2
Summary: Ambra 3D Viewer
Project-URL: Homepage, https://github.com/ramenguy99/xpg
Author-email: Dario Mylonopoulos <ramenguy99@gmail.com>
License-Expression: MIT
License-File: LICENSE
Requires-Python: >=3.8
Requires-Dist: numpy>=1.22
Requires-Dist: platformdirs<5,>=4
Requires-Dist: pyglm<3,>=2
Requires-Dist: pyxpg
